traverseCraft/__init__.py
traverseCraft/agent.py
traverseCraft/dataStructures.py
traverseCraft/iconHashInfo.py
traverseCraft/mcWorld.py
traverseCraft/mcWorldAgent.py
traverseCraft/world.py
traverseCraft/icons/100_Red Mushroom Block.png
traverseCraft/icons/101_Iron Bars.png
traverseCraft/icons/102_Glass Pane.png
traverseCraft/icons/103_Melon Block.png
traverseCraft/icons/108_Brick Stairs.png
traverseCraft/icons/109_Stone Brick Stairs.png
traverseCraft/icons/10_Flowing Lava.png
traverseCraft/icons/110_Mycelium.png
traverseCraft/icons/112_Nether Brick.png
traverseCraft/icons/114_Nether Brick Stairs.png
traverseCraft/icons/116_Enchantment Table.png
traverseCraft/icons/117_Brewing Stand.png
traverseCraft/icons/118_Cauldron.png
traverseCraft/icons/119_End Portal.png
traverseCraft/icons/11_Still Lava.png
traverseCraft/icons/120_End Portal Frame.png
traverseCraft/icons/121_End Stone.png
traverseCraft/icons/122_Dragon Egg.png
traverseCraft/icons/123_Redstone Lamp (inactive).png
traverseCraft/icons/124_Redstone Lamp (active).png
traverseCraft/icons/125_1_Double Spruce Wood Slab.png
traverseCraft/icons/125_2_Double Birch Wood Slab.png
traverseCraft/icons/125_3_Double Jungle Wood Slab.png
traverseCraft/icons/125_4_Double Acacia Wood Slab.png
traverseCraft/icons/125_5_Double Dark Oak Wood Slab.png
traverseCraft/icons/125_Double Oak Wood Slab.png
traverseCraft/icons/126_1_Spruce Wood Slab.png
traverseCraft/icons/126_2_Birch Wood Slab.png
traverseCraft/icons/126_3_Jungle Wood Slab.png
traverseCraft/icons/126_4_Acacia Wood Slab.png
traverseCraft/icons/126_5_Dark Oak Wood Slab.png
traverseCraft/icons/126_Oak Wood Slab.png
traverseCraft/icons/127_Cocoa.png
traverseCraft/icons/128_Sandstone Stairs.png
traverseCraft/icons/129_Emerald Ore.png
traverseCraft/icons/12_1_Red Sand.png
traverseCraft/icons/12_Sand.png
traverseCraft/icons/130_Ender Chest.png
traverseCraft/icons/131_Tripwire Hook.png
traverseCraft/icons/133_Emerald Block.png
traverseCraft/icons/134_Spruce Wood Stairs.png
TraverseCraft-1.0.3.dist-info/LICENCE
TraverseCraft-1.0.3.dist-info/METADATA
TraverseCraft-1.0.3.dist-info/WHEEL
TraverseCraft-1.0.3.dist-info/top_level.txt
TraverseCraft-1.0.3.dist-info/RECORD
