Metadata-Version: 2.1
Name: TraverseCraft
Version: 1.0.3
Summary: A Cross-Platform Real-Time Algorithm Simulation Tool
Home-page: https://harrionparrix.github.io/traversecraft/
Author: Srajan Chourasia, Varun Patrikar
Author-email: srajanstark.ash@gmail.com, patrikarvarun@gmail.com
Maintainer: Varun Patrikar, Srajan Chourasia
Maintainer-email: patrikarvarun@gmail.com, srajanstark.ash@gmail.com
Project-URL: Documentation, https://harrionparrix.github.io/traversecraft/user-guide/index.html
Project-URL: Source, https://github.com/srajan-kiyotaka/TraverseCraft/tree/main
Project-URL: Tracker, https://github.com/srajan-kiyotaka/TraverseCraft/issues
Project-URL: Reference, https://harrionparrix.github.io/traversecraft/references/world/World.html
Keywords: algorithms,simulation,real-time,tkinter,education,research,visualization,machine learning,reinforcement learning,artificial intelligence,agent-based modeling,cross-platform,dynamic heatmap,world generation,customizable,interactive,framework,algorithm visualization,graph traversal,tree traversal,grid world
Classifier: Development Status :: 5 - Production/Stable
Classifier: Intended Audience :: Developers
Classifier: Intended Audience :: Education
Classifier: License :: OSI Approved :: MIT License
Classifier: Operating System :: OS Independent
Classifier: Programming Language :: Python :: 3
Classifier: Topic :: Education
Classifier: Topic :: Software Development :: Libraries
Classifier: Topic :: Software Development :: Libraries :: Python Modules
Classifier: Topic :: Scientific/Engineering :: Artificial Intelligence
Classifier: Topic :: Scientific/Engineering :: Visualization
Requires-Python: >=3.6
License-File: LICENCE
Requires-Dist: prettytable
